pretty_text_rak/__init__.py
pretty_text_rak/pretty.py
pretty_text_rak-0.1.1.dist-info/WHEEL
pretty_text_rak-0.1.1.dist-info/METADATA
pretty_text_rak-0.1.1.dist-info/RECORD
